README.md
setup.py
liteco/__init__.py
liteco/__main__.py
liteco/liteco.py
liteco.egg-info/PKG-INFO
liteco.egg-info/SOURCES.txt
liteco.egg-info/dependency_links.txt
liteco.egg-info/top_level.txt