Metadata-Version: 1.1
Name: liteco
Version: 1.1.1
Summary: A simple Python program to add colors to your terminal application
Home-page: https://primidac@bitbucket.org/primidac/liteco.git
Author: Primidac
Author-email: primidac@gmail.com
License: MIT
Platform: UNKNOWN
Classifier: License :: OSI Approved :: MIT License
Classifier: Programming Language :: Python :: 3
Classifier: Programming Language :: Python :: 3.7
